installtool.py
mylog.py
installtool-1.0.dist-info/METADATA
installtool-1.0.dist-info/WHEEL
installtool-1.0.dist-info/entry_points.txt
installtool-1.0.dist-info/top_level.txt
installtool-1.0.dist-info/RECORD
