Metadata-Version: 2.1
Name: installtool
Version: 1.0
Summary: Perform remote installs using yaml runbooks
Home-page: https://github.com/l0r3zz/public/tree/master/installtool
Author: Geoff White
Author-email: geoffw@ambientnetworks.org
License: Apache 2.0
Keywords: install automation remote yaml
Platform: UNKNOWN
Classifier: Development Status :: 5 - Production/Stable
Classifier: Intended Audience :: System Administrators
Classifier: Topic :: Software Development :: Build Tools
Classifier: License :: OSI Approved :: Apache Software License
Classifier: Programming Language :: Python :: 3
Classifier: Programming Language :: Python :: 3.2
Classifier: Programming Language :: Python :: 3.3
Classifier: Programming Language :: Python :: 3.4
Classifier: Programming Language :: Python :: 3.5
Classifier: Programming Language :: Python :: 3.6
Classifier: Programming Language :: Python :: 3.7
Requires-Python: >=3
Requires-Dist: pexpect
